Workbook

Sheet Tesla DCF Model
A1: Tesla DCF Model 2024
A2: Max Wilson
A4: VALUATION SUMMARY | C4: KEY ASSUMPTIONS
A5: Enterprise Value | B5: =Valuation!E4 -> 10040.254 | C5: Base Year (Actual) | D5: 2024
A6: Net Cash | B6: =Valuation!E8 -> 22773 | C6: Revenue Growth 2025 | D6: =Assumptions!B3 -> 0.02
A7: Equity Value | B7: =Valuation!E5 -> 32813.254 | C7: EBIT Margin | D7: =Assumptions!B10 -> 0.075
A8: Shares Outstanding | B8: =Valuation!E7 -> 3216 | C8: WACC | D8: =Assumptions!B19 -> 0.1
A9: Intrinsic Value/Share | B9: =Valuation!E6 -> 10.203126 | C9: Terminal Growth | D9: =Assumptions!B20 -> 0.025

Sheet Assumptions
A1: ASSUMPTIONS | B1: VALUE | C1: WHY
A2: REVENUE ASSUMPTIONS
A3: Revenue Growth 2025 | B3: 0.02
A4: Revenue Growth 2026 | B4: 0.025
A5: Revenue Growth 2027 | B5: 0.03 | C5: Growth grows slowly (2024 < 1%)
A6: Revenue Growth 2028 | B6: 0.03
A7: Revenue Growth 2029 | B7: 0.03
A9: OPERATING ASSUMPTIONS
A10: EBIT Margin | B10: 0.075 | C10: Slight normalization above 2024
A11: Tax Rate | B11: 0.23 | C11: Normalized statutory
A13: REINVESTMENT ASSUMPTIONS
A14: Depreciation (% of revenue) | B14: 0.05 | C14: Historical avg
A15: CapEx (% of revenue) | B15: 0.1 | C15: Slightly lower than 2024
A16: Δ Working Capital (% of revenue) | B16: 0.01 | C16: Conservative
A18: DISCOUNT RATE & TERMINAL ASSUMPTIONS
A19: WACC | B19: 0.1 | C19: Equity-heavy, volatile
A20: Terminal Growth | B20: 0.025 | C20: ≤ nominal GDP

Sheet Historical_Financials
A1: ITEM | B1: 2024 ACTUAL
A2: Revenue | B2: 97690
A3: EBIT (Operating Income) | B3: 7076
A4: EBIT Margin | B4: 0.0724
A5: Depreciation & Amortization | B5: 5368
A6: Capital Expenditures | B6: 11339
A7: Free Cash Flow (reported) | B7: 3584
A8: Cash & Investments | B8: 36563
A9: Total Debt | B9: 13790
A10: Shares Outstanding | B10: 3216
A12: NON-OPERATING ITEMS (2024)
A13: Cash & Cash Equivalents | B13: 29094
A14: Short-Term Investments 7,469 | B14: 7469
A15: Total Cash & Investments | B15: 36563
A16: Total Debt | B16: 13790
A18: Source: Tesla 2024 10-K / Yahoo Finance
A19: Figures in USD millions

Sheet Forecast
A1: Year | B1: REVENUE | D1: YEAR | E1: EBIT | F1: NOPAT | G1: DEPRECIATION | H1: CAPEX | I1: ΔWC | J1: FCF
A2: 2024 | B2: 97690 | D2: 2025 | E2: =Forecast!B3*Assumptions!B10 -> 7473.285 | F2: =E2*(1-Assumptions!B11) -> 5754.4294 | G2: =Forecast!B3*Assumptions!B14 -> 4982.19 | H2: =Forecast!B3*Assumptions!B15 -> 9964.38 | I2: =(Forecast!B3-Forecast!B2)*Assumptions!B16 -> 19.538 | J2: =Forecast!F2+Forecast!G2-Forecast!H2-Forecast!I2 -> 752.70145
A3: 2025 | B3: =B2*1.02 -> 99643.8 | D3: 2026 | E3: =Forecast!B4*Assumptions!B10 -> 7660.1171 | F3: =E3*(1-Assumptions!B11) -> 5898.2902 | G3: =Forecast!B4*Assumptions!B14 -> 5106.7447 | H3: =Forecast!B4*Assumptions!B15 -> 10213.489 | I3: =(Forecast!B4-Forecast!B3)*Assumptions!B16 -> 24.91095 | J3: =Forecast!F3+Forecast!G3-Forecast!H3-Forecast!I3 -> 766.63449
A4: 2026 | B4: =B3*1.025 -> 102134.89 | D4: 2027 | E4: =Forecast!B5*Assumptions!B10 -> 7889.9206 | F4: =E4*(1-Assumptions!B11) -> 6075.2389 | G4: =Forecast!B5*Assumptions!B14 -> 5259.9471 | H4: =Forecast!B5*Assumptions!B15 -> 10519.894 | I4: =(Forecast!B5-Forecast!B4)*Assumptions!B16 -> 30.640468 | J4: =Forecast!F4+Forecast!G4-Forecast!H4-Forecast!I4 -> 784.65133
A5: 2027 | B5: =B4*1.03 -> 105198.94 | D5: 2028 | E5: =Forecast!B6*Assumptions!B10 -> 8126.6183 | F5: =E5*(1-Assumptions!B11) -> 6257.4961 | G5: =Forecast!B6*Assumptions!B14 -> 5417.7455 | H5: =Forecast!B6*Assumptions!B15 -> 10835.491 | I5: =(Forecast!B6-Forecast!B5)*Assumptions!B16 -> 31.559683 | J5: =Forecast!F5+Forecast!G5-Forecast!H5-Forecast!I5 -> 808.19087
A6: 2028 | B6: =B5*1.03 -> 108354.91 | D6: 2029 | E6: =Forecast!B7*Assumptions!B10 -> 8370.4168 | F6: =E6*(1-Assumptions!B11) -> 6445.2209 | G6: =Forecast!B7*Assumptions!B14 -> 5580.2779 | H6: =Forecast!B7*Assumptions!B15 -> 11160.556 | I6: =(Forecast!B7-Forecast!B6)*Assumptions!B16 -> 32.506473 | J6: =Forecast!F6+Forecast!G6-Forecast!H6-Forecast!I6 -> 832.4366
A7: 2029 | B7: =B6*1.03 -> 111605.56

Sheet Valuation
A1: DF | B1: PV of FCF | D1: Valuation
A2: =1/(1.1^1) -> 0.90909091 | B2: =A2*Forecast!J2 -> 684.27405 | D2: Terminal Value: | E2: =(Forecast!J6*(1+ Assumptions!B20))/(Assumptions!B19-Assumptions!B20) -> 11376.633
A3: =1/(1.1^2) -> 0.82644628 | B3: =A3*Forecast!J3 -> 633.58222 | D3: Present Value of TV: | E3: =E2*Valuation!A6 -> 7063.9943
A4: =1/(1.1^3) -> 0.7513148 | B4: =A4*Forecast!J4 -> 589.52016 | D4: Enterprise Value: | E4: =Valuation!E3+(Valuation!B2+Valuation!B3+Valuation!B4+Valuation!B5+Valuation!B6) -> 10040.254
A5: =1/(1.1^4) -> 0.68301346 | B5: =A5*Forecast!J5 -> 552.00524 | D5: Equity Value: | E5: =E4-(Historical_Financials!B9-Historical_Financials!B8) -> 32813.254
A6: =1/(1.1^5) -> 0.62092132 | B6: =A6*Forecast!J6 -> 516.87763 | D6: Intrinsic Value Per Share: | E6: =Valuation!E5/Historical_Financials!B10 -> 10.203126
D7: Shares Outstanding: | E7: =Historical_Financials!B10 -> 3216
D8: Net Cash: | E8: =Historical_Financials!B8-Historical_Financials!B9 -> 22773
